<item>
	<title>[COLOR=white]The Case of the Missing[/COLOR]</title>
	<meta>
	<imdb>tt0101149</imdb>
	<content>episode</content>
	<tvshowtitle>Murder Most Horrid</tvshowtitle>
	<year>1991</year>
	<season>1</season>
	<episode>1</episode>
	</meta>
	<link>https://rg.to/file/2451baf840381b2b8a15dda6c2992625/Murder_Most_Horrid_S01E01.avi.html</link>
	<thumbnail>https://image.tmdb.org/t/p/w1280/m1SlC839s2p5H3yS2MPrIcppWDf.jpg</thumbnail>
	<fanart>https://image.tmdb.org/t/p/w1280None</fanart>
</item>
<item>
	<title>[COLOR=white]The Girl from Ipanema[/COLOR]</title>
	<meta>
	<imdb>tt0101149</imdb>
	<content>episode</content>
	<tvshowtitle>Murder Most Horrid</tvshowtitle>
	<year>1991</year>
	<season>1</season>
	<episode>2</episode>
	</meta>
	<link>https://rg.to/file/6957286cf72085ac0dd812b2fcf845b8/Murder_Most_Horrid_S01E02.avi.html</link>
	<thumbnail>https://image.tmdb.org/t/p/w1280/cACaPXbKWXw51maBGA5SqYGYHuQ.jpg</thumbnail>
	<fanart>https://image.tmdb.org/t/p/w1280None</fanart>
</item>
<item>
	<title>[COLOR=white]He Died a Death[/COLOR]</title>
	<meta>
	<imdb>tt0101149</imdb>
	<content>episode</content>
	<tvshowtitle>Murder Most Horrid</tvshowtitle>
	<year>1991</year>
	<season>1</season>
	<episode>3</episode>
	</meta>
	<link>https://rg.to/file/43e37f69d3e3c466d58cf289a31e920f/Murder_Most_Horrid_S01E03.avi.html</link>
	<thumbnail>https://image.tmdb.org/t/p/w1280/5a4dDbvdt5zOkoOPLB6H5eCMBms.jpg</thumbnail>
	<fanart>https://image.tmdb.org/t/p/w1280None</fanart>
</item>
<item>
	<title>[COLOR=white]A Determined Woman[/COLOR]</title>
	<meta>
	<imdb>tt0101149</imdb>
	<content>episode</content>
	<tvshowtitle>Murder Most Horrid</tvshowtitle>
	<year>1991</year>
	<season>1</season>
	<episode>4</episode>
	</meta>
	<link>https://rg.to/file/d7c8974ca1a85fc0991062b8b3980b45/Murder_Most_Horrid_S01E04.avi.html</link>
	<thumbnail>https://image.tmdb.org/t/p/w1280/oZ8q93UeSrp0w6R8FLvRRydzop1.jpg</thumbnail>
	<fanart>https://image.tmdb.org/t/p/w1280None</fanart>
</item>
<item>
	<title>[COLOR=white]Murder at Tea Time[/COLOR]</title>
	<meta>
	<imdb>tt0101149</imdb>
	<content>episode</content>
	<tvshowtitle>Murder Most Horrid</tvshowtitle>
	<year>1991</year>
	<season>1</season>
	<episode>5</episode>
	</meta>
	<link>https://rg.to/file/7346a4c1d26c4d441d15badbdc6d01c1/Murder_Most_Horrid_S01E05.avi.html</link>
	<thumbnail>https://image.tmdb.org/t/p/w1280/6RwISnrityVooX4U18cxCO6UHAb.jpg</thumbnail>
	<fanart>https://image.tmdb.org/t/p/w1280None</fanart>
</item>
<item>
	<title>[COLOR=white]Mrs Hat and Mrs Red[/COLOR]</title>
	<meta>
	<imdb>tt0101149</imdb>
	<content>episode</content>
	<tvshowtitle>Murder Most Horrid</tvshowtitle>
	<year>1991</year>
	<season>1</season>
	<episode>6</episode>
	</meta>
	<link>https://rg.to/file/f2bb3c4b68ed7da4616d96b343995e29/Murder_Most_Horrid_S01E06.avi.html</link>
	<thumbnail>https://image.tmdb.org/t/p/w1280</thumbnail>
	<fanart>https://image.tmdb.org/t/p/w1280None</fanart>
</item>
