<item>
	<title>[COLOR=white]Good Police[/COLOR]</title>
	<meta>
	<imdb>tt4118584</imdb>
	<content>episode</content>
	<tvshowtitle>Shades of Blue</tvshowtitle>
	<year>2018</year>
	<season>3</season>
	<episode>1</episode>
	</meta>
	<link>https://myvidplay.com/d/j1eu1weifwbe</link>
	<thumbnail>https://image.tmdb.org/t/p/w1280/7t9tGSzfz7SeEaVGhcYs1kPWxra.jpg</thumbnail>
	<fanart>https://image.tmdb.org/t/p/w1280/9yxDAdbBqiZn8j93nzJMlQJDZur.jpg</fanart>
</item>
<item>
	<title>[COLOR=white]The Hollow Crown[/COLOR]</title>
	<meta>
	<imdb>tt4118584</imdb>
	<content>episode</content>
	<tvshowtitle>Shades of Blue</tvshowtitle>
	<year>2018</year>
	<season>3</season>
	<episode>2</episode>
	</meta>
	<link>https://myvidplay.com/d/mnat27v0fqt8</link>
	<thumbnail>https://image.tmdb.org/t/p/w1280/8EPRKkQKBBL4JbkXD453pq2CRkI.jpg</thumbnail>
	<fanart>https://image.tmdb.org/t/p/w1280/9yxDAdbBqiZn8j93nzJMlQJDZur.jpg</fanart>
</item>
<item>
	<title>[COLOR=white]That Way Madness Lies[/COLOR]</title>
	<meta>
	<imdb>tt4118584</imdb>
	<content>episode</content>
	<tvshowtitle>Shades of Blue</tvshowtitle>
	<year>2018</year>
	<season>3</season>
	<episode>3</episode>
	</meta>
	<link>https://myvidplay.com/d/eld74b5tg0tx</link>
	<thumbnail>https://image.tmdb.org/t/p/w1280/3mN7XBUphUoM0XHlLfNTRAXQgGx.jpg</thumbnail>
	<fanart>https://image.tmdb.org/t/p/w1280/9yxDAdbBqiZn8j93nzJMlQJDZur.jpg</fanart>
</item>
<item>
	<title>[COLOR=white]A Walking Shadow[/COLOR]</title>
	<meta>
	<imdb>tt4118584</imdb>
	<content>episode</content>
	<tvshowtitle>Shades of Blue</tvshowtitle>
	<year>2018</year>
	<season>3</season>
	<episode>4</episode>
	</meta>
	<link>https://myvidplay.com/d/c3h7ag0pwvi3</link>
	<thumbnail>https://image.tmdb.org/t/p/w1280/rZ8vR9Ivl0YgtpMaM3acGQSxHUq.jpg</thumbnail>
	<fanart>https://image.tmdb.org/t/p/w1280/9yxDAdbBqiZn8j93nzJMlQJDZur.jpg</fanart>
</item>
<item>
	<title>[COLOR=white]The Blue Wall[/COLOR]</title>
	<meta>
	<imdb>tt4118584</imdb>
	<content>episode</content>
	<tvshowtitle>Shades of Blue</tvshowtitle>
	<year>2018</year>
	<season>3</season>
	<episode>5</episode>
	</meta>
	<link>https://myvidplay.com/d/25g7cqae08tb</link>
	<thumbnail>https://image.tmdb.org/t/p/w1280/jLx1cIcwou64LBSt8MX2sCfcGsy.jpg</thumbnail>
	<fanart>https://image.tmdb.org/t/p/w1280/9yxDAdbBqiZn8j93nzJMlQJDZur.jpg</fanart>
</item>
<item>
	<title>[COLOR=white]The Reckoning[/COLOR]</title>
	<meta>
	<imdb>tt4118584</imdb>
	<content>episode</content>
	<tvshowtitle>Shades of Blue</tvshowtitle>
	<year>2018</year>
	<season>3</season>
	<episode>6</episode>
	</meta>
	<link>https://myvidplay.com/d/58rwntk8ey37</link>
	<thumbnail>https://image.tmdb.org/t/p/w1280/AhXfCKZij6zmIcJlfPmtc9DdiAn.jpg</thumbnail>
	<fanart>https://image.tmdb.org/t/p/w1280/9yxDAdbBqiZn8j93nzJMlQJDZur.jpg</fanart>
</item>
<item>
	<title>[COLOR=white]Straight Through the Heart[/COLOR]</title>
	<meta>
	<imdb>tt4118584</imdb>
	<content>episode</content>
	<tvshowtitle>Shades of Blue</tvshowtitle>
	<year>2018</year>
	<season>3</season>
	<episode>7</episode>
	</meta>
	<link>https://myvidplay.com/d/k6qvk7h6hba2</link>
	<thumbnail>https://image.tmdb.org/t/p/w1280/nIjZGsJsDUSkXZCzWdKX0tb6aDs.jpg</thumbnail>
	<fanart>https://image.tmdb.org/t/p/w1280/9yxDAdbBqiZn8j93nzJMlQJDZur.jpg</fanart>
</item>
<item>
	<title>[COLOR=white]Cry Havoc[/COLOR]</title>
	<meta>
	<imdb>tt4118584</imdb>
	<content>episode</content>
	<tvshowtitle>Shades of Blue</tvshowtitle>
	<year>2018</year>
	<season>3</season>
	<episode>8</episode>
	</meta>
	<link>https://myvidplay.com/d/zi6tvgr5hb4r</link>
	<thumbnail>https://image.tmdb.org/t/p/w1280/xi66pYMfmKfdg3gkbHD9N8CMAIl.jpg</thumbnail>
	<fanart>https://image.tmdb.org/t/p/w1280/9yxDAdbBqiZn8j93nzJMlQJDZur.jpg</fanart>
</item>
<item>
	<title>[COLOR=white]Goodnight, Sweet Prince[/COLOR]</title>
	<meta>
	<imdb>tt4118584</imdb>
	<content>episode</content>
	<tvshowtitle>Shades of Blue</tvshowtitle>
	<year>2018</year>
	<season>3</season>
	<episode>9</episode>
	</meta>
	<link>https://myvidplay.com/d/cswk8c4q5arw</link>
	<thumbnail>https://image.tmdb.org/t/p/w1280/rMzMUpM0KImUuMNa0VIVxwEk51S.jpg</thumbnail>
	<fanart>https://image.tmdb.org/t/p/w1280/9yxDAdbBqiZn8j93nzJMlQJDZur.jpg</fanart>
</item>
<item>
	<title>[COLOR=white]By Virtue Fall[/COLOR]</title>
	<meta>
	<imdb>tt4118584</imdb>
	<content>episode</content>
	<tvshowtitle>Shades of Blue</tvshowtitle>
	<year>2018</year>
	<season>3</season>
	<episode>10</episode>
	</meta>
	<link>https://myvidplay.com/d/i1drfi3dnobg</link>
	<thumbnail>https://image.tmdb.org/t/p/w1280/jQ98qz6OOI61ofWK0UUof5PKof6.jpg</thumbnail>
	<fanart>https://image.tmdb.org/t/p/w1280/9yxDAdbBqiZn8j93nzJMlQJDZur.jpg</fanart>
</item>
