<dir>
	<title>[COLOR=white]Season 1[/COLOR]</title>
	<meta>
	<imdb>tt0408403</imdb>
	<content>season</content>
	<season>1</season>
	<year>2001</year>
	</meta>
	<link>http://www.ezzer-mac.com/Addon/text/tvseries/mlaw/ml1.xml</link>
	<thumbnail>https://image.tmdb.org/t/p/w1280/uaYGTVr0dHJ6Ustk55TSnjj21u5.jpg</thumbnail>
	<fanart>https://image.tmdb.org/t/p/w1280/wVA9YbKbH7qbSpsESHoUXJVWRO0.jpg</fanart>
</dir>
<dir>
	<title>[COLOR=white]Season 2[/COLOR]</title>
	<meta>
	<imdb>tt0408403</imdb>
	<content>season</content>
	<season>2</season>
	<year>2004</year>
	</meta>
	<link>http://www.ezzer-mac.com/Addon/text/tvseries/mlaw/ml2.xml</link>
	<thumbnail>https://image.tmdb.org/t/p/w1280/sJZBNteAbqEfqWcIu4ml9wHFVag.jpg</thumbnail>
	<fanart>https://image.tmdb.org/t/p/w1280/wVA9YbKbH7qbSpsESHoUXJVWRO0.jpg</fanart>
</dir>
<dir>
	<title>[COLOR=white]Season 3[/COLOR]</title>
	<meta>
	<imdb>tt0408403</imdb>
	<content>season</content>
	<season>3</season>
	<year>2005</year>
	</meta>
	<link>http://www.ezzer-mac.com/Addon/text/tvseries/mlaw/ml3.xml</link>
	<thumbnail>https://image.tmdb.org/t/p/w1280/nhLZvFnM16bxxEQpCeUy6LNsCsL.jpg</thumbnail>
	<fanart>https://image.tmdb.org/t/p/w1280/wVA9YbKbH7qbSpsESHoUXJVWRO0.jpg</fanart>
</dir>
<dir>
	<title>[COLOR=white]Season 4[/COLOR]</title>
	<meta>
	<imdb>tt0408403</imdb>
	<content>season</content>
	<season>4</season>
	<year>2006</year>
	</meta>
	<link>http://www.ezzer-mac.com/Addon/text/tvseries/mlaw/ml4.xml</link>
	<thumbnail>https://image.tmdb.org/t/p/w1280/rKCnHfVlcDZD7GKdhleYVi3ykRn.jpg</thumbnail>
	<fanart>https://image.tmdb.org/t/p/w1280/wVA9YbKbH7qbSpsESHoUXJVWRO0.jpg</fanart>
</dir>
<dir>
	<title>[COLOR=white]Season 5[/COLOR]</title>
	<meta>
	<imdb>tt0408403</imdb>
	<content>season</content>
	<season>5</season>
	<year>2007</year>
	</meta>
	<link>http://www.ezzer-mac.com/Addon/text/tvseries/mlaw/ml5.xml</link>
	<thumbnail>https://image.tmdb.org/t/p/w1280/o2tYYfgDLxtfDckUlJ5xV6yOKVr.jpg</thumbnail>
	<fanart>https://image.tmdb.org/t/p/w1280/wVA9YbKbH7qbSpsESHoUXJVWRO0.jpg</fanart>
</dir>
