<item>
	<title>[COLOR=white]Series 1[/COLOR]</title>
	<meta>
	<imdb>tt0491807</imdb>
	<content>episode</content>
	<tvshowtitle>See No Evil The Moors Murders</tvshowtitle>
	<year>2006</year>
	<season>1</season>
	<episode>1</episode>
	</meta>
	<link>https://myvidplay.com/d/z662k7mp7d4h</link>
	<thumbnail>https://image.tmdb.org/t/p/w1280</thumbnail>
	<fanart>https://image.tmdb.org/t/p/w1280None</fanart>
</item>
<item>
	<title>[COLOR=white]Series 2[/COLOR]</title>
	<meta>
	<imdb>tt0491807</imdb>
	<content>episode</content>
	<tvshowtitle>See No Evil The Moors Murders</tvshowtitle>
	<year>2006</year>
	<season>1</season>
	<episode>1</episode>
	</meta>
	<link>https://myvidplay.com/d/l4lxqqd7w7fx</link>
	<thumbnail>https://image.tmdb.org/t/p/w1280</thumbnail>
	<fanart>https://image.tmdb.org/t/p/w1280None</fanart>
</item>

