<item>
	<title>[COLOR=white]Sniper's Nest, Part 1[/COLOR]</title>
	<meta>
	<imdb>tt0115355</imdb>
	<content>episode</content>
	<tvshowtitle>Silent Witness</tvshowtitle>
	<year>2015</year>
	<season>18</season>
	<episode>1</episode>
	</meta>
	<link>https://dood.re/d/h31whtdz3u6c</link>
	<thumbnail>https://image.tmdb.org/t/p/w1280/l9J9lGf7FbSICXXyR99qS9PRqip.jpg</thumbnail>
	<fanart>https://image.tmdb.org/t/p/w1280/5WmkDjpgqwO3nU11YEmlSSx8YhH.jpg</fanart>
</item>
<item>
	<title>[COLOR=white]Sniper's Nest, Part 2[/COLOR]</title>
	<meta>
	<imdb>tt0115355</imdb>
	<content>episode</content>
	<tvshowtitle>Silent Witness</tvshowtitle>
	<year>2015</year>
	<season>18</season>
	<episode>2</episode>
	</meta>
	<link>https://dood.re/d/bw51w3hb5fle</link>
	<thumbnail>https://image.tmdb.org/t/p/w1280/vE7QsCRIYEeyHIyv2o1vjCarhlZ.jpg</thumbnail>
	<fanart>https://image.tmdb.org/t/p/w1280/5WmkDjpgqwO3nU11YEmlSSx8YhH.jpg</fanart>
</item>
<item>
	<title>[COLOR=white]Falling Angels, Part 1[/COLOR]</title>
	<meta>
	<imdb>tt0115355</imdb>
	<content>episode</content>
	<tvshowtitle>Silent Witness</tvshowtitle>
	<year>2015</year>
	<season>18</season>
	<episode>3</episode>
	</meta>
	<link>https://dood.re/d/k904j75rss07</link>
	<thumbnail>https://image.tmdb.org/t/p/w1280/vJFHPFLkLVaojfTRIpseEazvwhc.jpg</thumbnail>
	<fanart>https://image.tmdb.org/t/p/w1280/5WmkDjpgqwO3nU11YEmlSSx8YhH.jpg</fanart>
</item>
<item>
	<title>[COLOR=white]Falling Angels, Part 2[/COLOR]</title>
	<meta>
	<imdb>tt0115355</imdb>
	<content>episode</content>
	<tvshowtitle>Silent Witness</tvshowtitle>
	<year>2015</year>
	<season>18</season>
	<episode>4</episode>
	</meta>
	<link>https://rg.to/file/bd5e6f5150b3080e205a2260d8f76205/Silent.Witness.S18E04.DVDRip.x264-HAGGiS.mkv.html</link>
	<thumbnail>https://image.tmdb.org/t/p/w1280/7MlX6P7d82SQeCOt8TTJxTvc0xx.jpg</thumbnail>
	<fanart>https://image.tmdb.org/t/p/w1280/5WmkDjpgqwO3nU11YEmlSSx8YhH.jpg</fanart>
</item>
<item>
	<title>[COLOR=white]Protection, Part 1[/COLOR]</title>
	<meta>
	<imdb>tt0115355</imdb>
	<content>episode</content>
	<tvshowtitle>Silent Witness</tvshowtitle>
	<year>2015</year>
	<season>18</season>
	<episode>5</episode>
	</meta>
	<link>https://dood.re/d/uf9zfaz0aj0p</link>
	<thumbnail>https://image.tmdb.org/t/p/w1280/pmvg1ghD0u7LahGUYT1LnmyA38w.jpg</thumbnail>
	<fanart>https://image.tmdb.org/t/p/w1280/5WmkDjpgqwO3nU11YEmlSSx8YhH.jpg</fanart>
</item>
<item>
	<title>[COLOR=white]Protection, Part 2[/COLOR]</title>
	<meta>
	<imdb>tt0115355</imdb>
	<content>episode</content>
	<tvshowtitle>Silent Witness</tvshowtitle>
	<year>2015</year>
	<season>18</season>
	<episode>6</episode>
	</meta>
	<link>https://dood.re/d/oo8wqwxffw9z</link>
	<thumbnail>https://image.tmdb.org/t/p/w1280/w9UHl0J74fsONxloSURhXUuuSD7.jpg</thumbnail>
	<fanart>https://image.tmdb.org/t/p/w1280/5WmkDjpgqwO3nU11YEmlSSx8YhH.jpg</fanart>
</item>
<item>
	<title>[COLOR=white]Squaring the Circle, Part 1[/COLOR]</title>
	<meta>
	<imdb>tt0115355</imdb>
	<content>episode</content>
	<tvshowtitle>Silent Witness</tvshowtitle>
	<year>2015</year>
	<season>18</season>
	<episode>7</episode>
	</meta>
	<link>https://dood.re/d/49zme041sl3h</link>
	<thumbnail>https://image.tmdb.org/t/p/w1280/geaasrvEoUao6GT59Bbp4mMHVkR.jpg</thumbnail>
	<fanart>https://image.tmdb.org/t/p/w1280/5WmkDjpgqwO3nU11YEmlSSx8YhH.jpg</fanart>
</item>
<item>
	<title>[COLOR=white]Squaring the Circle, Part 2[/COLOR]</title>
	<meta>
	<imdb>tt0115355</imdb>
	<content>episode</content>
	<tvshowtitle>Silent Witness</tvshowtitle>
	<year>2015</year>
	<season>18</season>
	<episode>8</episode>
	</meta>
	<link>https://rg.to/file/e9e1d55a52a481a45560086686cd7ea4/silent.witness.s18e08.dvdrip.x264-haggis.mkv.html</link>
	<thumbnail>https://image.tmdb.org/t/p/w1280/oP3mxOWHO0VDFXPCSifPQ4XKXAC.jpg</thumbnail>
	<fanart>https://image.tmdb.org/t/p/w1280/5WmkDjpgqwO3nU11YEmlSSx8YhH.jpg</fanart>
</item>
<item>
	<title>[COLOR=white]One of Our Own, Part 1[/COLOR]</title>
	<meta>
	<imdb>tt0115355</imdb>
	<content>episode</content>
	<tvshowtitle>Silent Witness</tvshowtitle>
	<year>2015</year>
	<season>18</season>
	<episode>9</episode>
	</meta>
	<link>https://dood.re/d/qvdqunv0zdz3</link>
	<thumbnail>https://image.tmdb.org/t/p/w1280/amJQgFCCUCOwmYkBQb9T44nPb54.jpg</thumbnail>
	<fanart>https://image.tmdb.org/t/p/w1280/5WmkDjpgqwO3nU11YEmlSSx8YhH.jpg</fanart>
</item>
<item>
	<title>[COLOR=white]One of Our Own, Part 2[/COLOR]</title>
	<meta>
	<imdb>tt0115355</imdb>
	<content>episode</content>
	<tvshowtitle>Silent Witness</tvshowtitle>
	<year>2015</year>
	<season>18</season>
	<episode>10</episode>
	</meta>
	<link>https://rg.to/file/d8a9e855f2b2d6b79248e82eb10485fa/Silent.Witness.S18E10.DVDRip.x264-HAGGiS.mkv.html</link>
	<thumbnail>https://image.tmdb.org/t/p/w1280/q2drCBKar7l21uOlMnbiG3PLfuJ.jpg</thumbnail>
	<fanart>https://image.tmdb.org/t/p/w1280/5WmkDjpgqwO3nU11YEmlSSx8YhH.jpg</fanart>
</item>
