<item>
	<title>[COLOR=white]Chapter 1: The Mandalorian[/COLOR]</title>
	<meta>
	<imdb>tt8111088</imdb>
	<content>episode</content>
	<tvshowtitle>The Mandalorian</tvshowtitle>
	<year>2019</year>
	<season>1</season>
	<episode>1</episode>
	</meta>
	<link>https://rg.to/file/27121beb0554dfb55cf1c34ce43a9ac2/The.Mndlrn.S01E01.WEBRip.x264-ION10.mp4.html</link>
	<thumbnail>https://image.tmdb.org/t/p/w1280/lr8OEa0GzjZ0qmD9NuuMj6TRWxF.jpg</thumbnail>
	<fanart>https://image.tmdb.org/t/p/w1280/9ijMGlJKqcslswWUzTEwScm82Gs.jpg</fanart>
</item>
<item>
	<title>[COLOR=white]Chapter 2: The Child[/COLOR]</title>
	<meta>
	<imdb>tt8111088</imdb>
	<content>episode</content>
	<tvshowtitle>The Mandalorian</tvshowtitle>
	<year>2019</year>
	<season>1</season>
	<episode>2</episode>
	</meta>
	<link>https://rg.to/file/01d48d1ccb09cae66c8b34d0c2530d0b/The.Mndlrn.S01E02.WEBRip.x264-ION10.mp4.html</link>
	<thumbnail>https://image.tmdb.org/t/p/w1280/b8y9qAq2ZdU27Ua1lJxyNQbmzQE.jpg</thumbnail>
	<fanart>https://image.tmdb.org/t/p/w1280/9ijMGlJKqcslswWUzTEwScm82Gs.jpg</fanart>
</item>
<item>
	<title>[COLOR=white]Chapter 3: The Sin[/COLOR]</title>
	<meta>
	<imdb>tt8111088</imdb>
	<content>episode</content>
	<tvshowtitle>The Mandalorian</tvshowtitle>
	<year>2019</year>
	<season>1</season>
	<episode>3</episode>
	</meta>
	<link>https://rg.to/file/209cba10565424a67f74ad33e555b554/The.Mndlrn.S01E03.WEBRip.x264-ION10.mp4.html</link>
	<thumbnail>https://image.tmdb.org/t/p/w1280/5wGkymV2D9P9ZGI2wP0PefIwFol.jpg</thumbnail>
	<fanart>https://image.tmdb.org/t/p/w1280/9ijMGlJKqcslswWUzTEwScm82Gs.jpg</fanart>
</item>
<item>
	<title>[COLOR=white]Chapter 4: Sanctuary[/COLOR]</title>
	<meta>
	<imdb>tt8111088</imdb>
	<content>episode</content>
	<tvshowtitle>The Mandalorian</tvshowtitle>
	<year>2019</year>
	<season>1</season>
	<episode>4</episode>
	</meta>
	<link>https://rg.to/file/32905b501818538d9ef429a136765c4d/The.Mndlrn.S01E04.WEBRip.x264-ION10.mp4.html</link>
	<thumbnail>https://image.tmdb.org/t/p/w1280/cKyE2gtQT5zIpLQHnD3mFNWrKud.jpg</thumbnail>
	<fanart>https://image.tmdb.org/t/p/w1280/9ijMGlJKqcslswWUzTEwScm82Gs.jpg</fanart>
</item>
<item>
	<title>[COLOR=white]Chapter 5: The Gunslinger[/COLOR]</title>
	<meta>
	<imdb>tt8111088</imdb>
	<content>episode</content>
	<tvshowtitle>The Mandalorian</tvshowtitle>
	<year>2019</year>
	<season>1</season>
	<episode>5</episode>
	</meta>
	<link>https://rg.to/file/4fe07695bac5d3e76df373fd1a2ac9a0/The.Mndlrn.S01E05.WEBRip.x264-ION10.mp4.html</link>
	<thumbnail>https://image.tmdb.org/t/p/w1280/o6enRShRThpenWqtaC5lXNsEa8w.jpg</thumbnail>
	<fanart>https://image.tmdb.org/t/p/w1280/9ijMGlJKqcslswWUzTEwScm82Gs.jpg</fanart>
</item>
<item>
	<title>[COLOR=white]Chapter 6: The Prisoner[/COLOR]</title>
	<meta>
	<imdb>tt8111088</imdb>
	<content>episode</content>
	<tvshowtitle>The Mandalorian</tvshowtitle>
	<year>2019</year>
	<season>1</season>
	<episode>6</episode>
	</meta>
	<link>https://rg.to/file/06e70b1b21a4b98fd9b4773406706cae/The.Mndlrn.S01E06.WEBRip.x264-ION10.mp4.html</link>
	<thumbnail>https://image.tmdb.org/t/p/w1280/7Z9Bc58uLnp8gIDGtdi0jNEqYZY.jpg</thumbnail>
	<fanart>https://image.tmdb.org/t/p/w1280/9ijMGlJKqcslswWUzTEwScm82Gs.jpg</fanart>
</item>
<item>
	<title>[COLOR=white]Chapter 7: The Reckoning[/COLOR]</title>
	<meta>
	<imdb>tt8111088</imdb>
	<content>episode</content>
	<tvshowtitle>The Mandalorian</tvshowtitle>
	<year>2019</year>
	<season>1</season>
	<episode>7</episode>
	</meta>
	<link>https://rg.to/file/79fbece00efcfe4120574b9514de279c/The.Mndlrn.S01E07.WEBRip.x264-ION10.mp4.html</link>
	<thumbnail>https://image.tmdb.org/t/p/w1280/m483Gihn8vAt0cW5RXe5YRtchIQ.jpg</thumbnail>
	<fanart>https://image.tmdb.org/t/p/w1280/9ijMGlJKqcslswWUzTEwScm82Gs.jpg</fanart>
</item>
<item>
	<title>[COLOR=white]Chapter 8: Redemption[/COLOR]</title>
	<meta>
	<imdb>tt8111088</imdb>
	<content>episode</content>
	<tvshowtitle>The Mandalorian</tvshowtitle>
	<year>2019</year>
	<season>1</season>
	<episode>8</episode>
	</meta>
	<link>https://rg.to/file/6c60ff8fe6b8b5dd712867afc05055a4/The.Mndlrn.S01E08.WEBRip.x264-ION10.mp4.html</link>
	<thumbnail>https://image.tmdb.org/t/p/w1280/v36aZwxTsPAvqsssLPVno3VFvg5.jpg</thumbnail>
	<fanart>https://image.tmdb.org/t/p/w1280/9ijMGlJKqcslswWUzTEwScm82Gs.jpg</fanart>
</item>
