<item>
	<title>[COLOR=white]Sleeping Murder[/COLOR]</title>
	<meta>
	<imdb>tt1734537</imdb>
	<content>episode</content>
	<tvshowtitle>Agatha Christie s Marple</tvshowtitle>
	<year>2006</year>
	<season>2</season>
	<episode>1</episode>
	</meta>
	<link>https://rg.to/file/8986de374d4301272b5fbb7ffe253c86/agatha.christies.marple.s02e01.avi.html</link>
	<thumbnail>https://image.tmdb.org/t/p/w1280/papT64KX9n8DbUKMu8dY9Mxea7M.jpg</thumbnail>
	<fanart>https://image.tmdb.org/t/p/w1280None</fanart>
</item>
<item>
	<title>[COLOR=white]The Moving Finger[/COLOR]</title>
	<meta>
	<imdb>tt1734537</imdb>
	<content>episode</content>
	<tvshowtitle>Agatha Christie s Marple</tvshowtitle>
	<year>2006</year>
	<season>2</season>
	<episode>2</episode>
	</meta>
	<link>https://rg.to/file/8986de374d4301272b5fbb7ffe253c86/agatha.christies.marple.s02e01.avi.html</link>
	<thumbnail>https://image.tmdb.org/t/p/w1280/tvjrEfopmqmVPyDXNWHP08iIS6Z.jpg</thumbnail>
	<fanart>https://image.tmdb.org/t/p/w1280None</fanart>
</item>
<item>
	<title>[COLOR=white]By the Pricking of My Thumbs[/COLOR]</title>
	<meta>
	<imdb>tt1734537</imdb>
	<content>episode</content>
	<tvshowtitle>Agatha Christie s Marple</tvshowtitle>
	<year>2006</year>
	<season>2</season>
	<episode>3</episode>
	</meta>
	<link>https://rg.to/file/b78fdf6aec39113e09cc55aa64fabd8d/agatha.christies.marple.s02e03.avi.html</link>
	<thumbnail>https://image.tmdb.org/t/p/w1280/jCaGzVRoFOgwvNJRt6Kq2B3SY83.jpg</thumbnail>
	<fanart>https://image.tmdb.org/t/p/w1280None</fanart>
</item>
<item>
	<title>[COLOR=white]The Sittaford Mystery[/COLOR]</title>
	<meta>
	<imdb>tt1734537</imdb>
	<content>episode</content>
	<tvshowtitle>Agatha Christie s Marple</tvshowtitle>
	<year>2006</year>
	<season>2</season>
	<episode>4</episode>
	</meta>
	<link>https://rg.to/file/d5cca4fa1a266bdd0e590fe9bc11a0bd/agatha.christies.marple.s02e04.avi.html</link>
	<thumbnail>https://image.tmdb.org/t/p/w1280/tLTYFozbUm8MsJLo1hP8v5v8WrY.jpg</thumbnail>
	<fanart>https://image.tmdb.org/t/p/w1280None</fanart>
</item>
