<item>
	<title>[COLOR=white]Mad Max[/COLOR]</title>
	<meta>
	<imdb>tt0079501</imdb>
	<content>movie</content>
	<title>Mad Max</title>
	<year>1979</year>
	</meta>
	<link>https://rapidgator.net/file/988ed889264e6c48d1f18e0a44499f79/Mad.Max.1979.iNTERNAL.BDRip.x264-LiBRARiANS.mkv.html</link>
	<thumbnail>https://image.tmdb.org/t/p/w1280/5LrI4GiCSrChgkdskVZiwv643Kg.jpg</thumbnail>
	<fanart>https://image.tmdb.org/t/p/w1280/yhF12g35SLnXvHC46KY1plZvjtG.jpg</fanart>
</item>
<item>
	<title>[COLOR=white]Mad Max 2[/COLOR]</title>
	<meta>
	<imdb>tt0082694</imdb>
	<content>movie</content>
	<title>Mad Max 2</title>
	<year>1981</year>
	</meta>
	<link>https://rapidgator.net/file/599f03fbf783c180aa2b52bfedde69af/Mad.Max.2.The.Road.Warrior.1980.1080p.BRrip.x264.YIFY.mp4.html</link>
	<thumbnail>https://image.tmdb.org/t/p/w1280/ffzRLeZaKP6YCaTVieWeSLccC4y.jpg</thumbnail>
	<fanart>https://image.tmdb.org/t/p/w1280/MMSI9WzRmOdqXarevQ3Kqnytrx.jpg</fanart>
</item>
<item>
	<title>[COLOR=white]Mad Max Beyond Thunderdome[/COLOR]</title>
	<meta>
	<imdb>tt0089530</imdb>
	<content>movie</content>
	<title>Mad Max Beyond Thunderdome</title>
	<year>1985</year>
	</meta>
	<link>https://rapidgator.net/file/8660ab61410d8762380489b4b6fd9549/Mad.Max.Beyond.Thunderdome.1985.2160p.4K.BluRay.x265.10bit.AAC5.1-YTS.MX.mkv.html</link>
	<thumbnail>https://image.tmdb.org/t/p/w1280/jJlxcEVVUHnrUeEkQ0077VeHQpb.jpg</thumbnail>
	<fanart>https://image.tmdb.org/t/p/w1280/cO8zcdPhLT3UdykkXCvfhIVrgHK.jpg</fanart>
</item>
<item>
	<title>[COLOR=white]Mad Max: Fury Road[/COLOR]</title>
	<meta>
	<imdb>tt1392190</imdb>
	<content>movie</content>
	<title>Mad Max: Fury Road</title>
	<year>2015</year>
	</meta>
	<link>https://rapidgator.net/file/d017980c08de251f3bd3c140a5c8cbbd/Mad.Max.Fury.Road.2015.1080p.BluRay.H264.AC3.DD5.1.mp4</link>
	<thumbnail>https://image.tmdb.org/t/p/w1280/8tZYtuWezp8JbcsvHYO0O46tFbo.jpg</thumbnail>
	<fanart>https://image.tmdb.org/t/p/w1280/nlCHUWjY9XWbuEUQauCBgnY8ymF.jpg</fanart>
</item>