<item>
	<title>[COLOR=white]Murdoch of the Klondike[/COLOR]</title>
	<meta>
	<imdb>tt1091909</imdb>
	<content>episode</content>
	<tvshowtitle>Murdoch Mysteries</tvshowtitle>
	<year>2012</year>
	<season>5</season>
	<episode>1</episode>
	</meta>
	<link>https://rg.to/file/893c86d9960146d9f6ddb08f3df677b1/Murdoch.Mysteries.S05E01.BDRip.XviD-aAF.avi.html</link>
	<thumbnail>https://image.tmdb.org/t/p/w1280/p9tOpOSDTyDvQHCCmrR53fjybKO.jpg</thumbnail>
	<fanart>https://image.tmdb.org/t/p/w1280/rmIrbTk6Qb08grYwJlGQok9VnGk.jpg</fanart>
</item>
<item>
	<title>[COLOR=white]Back and to the Left[/COLOR]</title>
	<meta>
	<imdb>tt1091909</imdb>
	<content>episode</content>
	<tvshowtitle>Murdoch Mysteries</tvshowtitle>
	<year>2012</year>
	<season>5</season>
	<episode>2</episode>
	</meta>
	<link>https://rg.to/file/30d5673274a3ca5578ce9447ebf17905/Murdoch.Mysteries.S05E02.back.and.to.the.left.avi.html</link>
	<thumbnail>https://image.tmdb.org/t/p/w1280/sZxOfGu6HNhKmnF5MB10k2ZHOab.jpg</thumbnail>
	<fanart>https://image.tmdb.org/t/p/w1280/rmIrbTk6Qb08grYwJlGQok9VnGk.jpg</fanart>
</item>
<item>
	<title>[COLOR=white]Evil Eye of Egypt[/COLOR]</title>
	<meta>
	<imdb>tt1091909</imdb>
	<content>episode</content>
	<tvshowtitle>Murdoch Mysteries</tvshowtitle>
	<year>2012</year>
	<season>5</season>
	<episode>3</episode>
	</meta>
	<link>https://rg.to/file/7c563be967f7a20bec8a93018a1e7a2f/Murdoch.Mysteries.S05E03.BDRip.XviD-aAF.avi.html</link>
	<thumbnail>https://image.tmdb.org/t/p/w1280/mxtBIyDgYhVkK0BTiUTDvmeiN5p.jpg</thumbnail>
	<fanart>https://image.tmdb.org/t/p/w1280/rmIrbTk6Qb08grYwJlGQok9VnGk.jpg</fanart>
</item>
<item>
	<title>[COLOR=white]War on Terror[/COLOR]</title>
	<meta>
	<imdb>tt1091909</imdb>
	<content>episode</content>
	<tvshowtitle>Murdoch Mysteries</tvshowtitle>
	<year>2012</year>
	<season>5</season>
	<episode>4</episode>
	</meta>
	<link>https://rg.to/file/228c1aa527db83ba92c30e608cd401ff/Murdoch.Mysteries.S05E04.BDRip.XviD-aAF.avi.html</link>
	<thumbnail>https://image.tmdb.org/t/p/w1280/7LJPLLA8VSjPWerWfYwB8AXynsW.jpg</thumbnail>
	<fanart>https://image.tmdb.org/t/p/w1280/rmIrbTk6Qb08grYwJlGQok9VnGk.jpg</fanart>
</item>
<item>
	<title>[COLOR=white]Murdoch at the Opera[/COLOR]</title>
	<meta>
	<imdb>tt1091909</imdb>
	<content>episode</content>
	<tvshowtitle>Murdoch Mysteries</tvshowtitle>
	<year>2012</year>
	<season>5</season>
	<episode>5</episode>
	</meta>
	<link>https://rg.to/file/8f73d9dd6df9fd3d210dc2c5db28df73/Murdoch.Mysteries.S05E05.TVRip.XviD.avi.html</link>
	<thumbnail>https://image.tmdb.org/t/p/w1280/zOuLxkIdkDnHcJ2oqNQ7VitxY1w.jpg</thumbnail>
	<fanart>https://image.tmdb.org/t/p/w1280/rmIrbTk6Qb08grYwJlGQok9VnGk.jpg</fanart>
</item>
<item>
	<title>[COLOR=white]Who Killed the Electric Carriage?[/COLOR]</title>
	<meta>
	<imdb>tt1091909</imdb>
	<content>episode</content>
	<tvshowtitle>Murdoch Mysteries</tvshowtitle>
	<year>2012</year>
	<season>5</season>
	<episode>6</episode>
	</meta>
	<link>https://rg.to/file/d4abb9aef652b250ad2130b0387429c7/Murdoch.Mysteries.S05E06.DVDRip.XviD-OSiTV.avi.html</link>
	<thumbnail>https://image.tmdb.org/t/p/w1280/3QYvclvozTSlquI2RYIunvkrl4D.jpg</thumbnail>
	<fanart>https://image.tmdb.org/t/p/w1280/rmIrbTk6Qb08grYwJlGQok9VnGk.jpg</fanart>
</item>
<item>
	<title>[COLOR=white]Stroll on the Wild Side Part 1[/COLOR]</title>
	<meta>
	<imdb>tt1091909</imdb>
	<content>episode</content>
	<tvshowtitle>Murdoch Mysteries</tvshowtitle>
	<year>2012</year>
	<season>5</season>
	<episode>7</episode>
	</meta>
	<link>https://rg.to/file/a269f8aa27df77e0f0daf5557b02caa7/Murdoch.Mysteries.S05E07.DVDRip.XviD-OSiTV.avi.html</link>
	<thumbnail>https://image.tmdb.org/t/p/w1280/4g8uf8wLAJdaibWdWSsbTjc4f8j.jpg</thumbnail>
	<fanart>https://image.tmdb.org/t/p/w1280/rmIrbTk6Qb08grYwJlGQok9VnGk.jpg</fanart>
</item>
<item>
	<title>[COLOR=white]Stroll on the Wild Side (Pt 2)[/COLOR]</title>
	<meta>
	<imdb>tt1091909</imdb>
	<content>episode</content>
	<tvshowtitle>Murdoch Mysteries</tvshowtitle>
	<year>2012</year>
	<season>5</season>
	<episode>8</episode>
	</meta>
	<link>https://rg.to/file/9150959a8308f72a9b0626a34cb8c9b6/Murdoch.Mysteries.S05E08.DVDRip.XviD-OSiTV.avi.html</link>
	<thumbnail>https://image.tmdb.org/t/p/w1280/h5gVrPESSYKCz9vX7S2rMXcTolh.jpg</thumbnail>
	<fanart>https://image.tmdb.org/t/p/w1280/rmIrbTk6Qb08grYwJlGQok9VnGk.jpg</fanart>
</item>
<item>
	<title>[COLOR=white]Invention Convention[/COLOR]</title>
	<meta>
	<imdb>tt1091909</imdb>
	<content>episode</content>
	<tvshowtitle>Murdoch Mysteries</tvshowtitle>
	<year>2012</year>
	<season>5</season>
	<episode>9</episode>
	</meta>
	<link>https://rg.to/file/567827b7ac79abe18bb364d55642a1c8/Murdoch.Mysteries.S05E09.DVDRip.XviD-OSiTV.avi.html</link>
	<thumbnail>https://image.tmdb.org/t/p/w1280/14moiEo08tm8l1EExkejFwmHW5b.jpg</thumbnail>
	<fanart>https://image.tmdb.org/t/p/w1280/rmIrbTk6Qb08grYwJlGQok9VnGk.jpg</fanart>
</item>
<item>
	<title>[COLOR=white]Staircase to Heaven[/COLOR]</title>
	<meta>
	<imdb>tt1091909</imdb>
	<content>episode</content>
	<tvshowtitle>Murdoch Mysteries</tvshowtitle>
	<year>2012</year>
	<season>5</season>
	<episode>10</episode>
	</meta>
	<link>https://streamlare.com/v/gLXEDVM0Z53nQY74/murdoch-mysteries-s05e10-bdrip-x264-pja-mkv</link>
	<thumbnail>https://image.tmdb.org/t/p/w1280/8Zf6t0mtg2ExjwcBWlTKtid725F.jpg</thumbnail>
	<fanart>https://image.tmdb.org/t/p/w1280/rmIrbTk6Qb08grYwJlGQok9VnGk.jpg</fanart>
</item>
<item>
	<title>[COLOR=white]Murdoch in Toyland[/COLOR]</title>
	<meta>
	<imdb>tt1091909</imdb>
	<content>episode</content>
	<tvshowtitle>Murdoch Mysteries</tvshowtitle>
	<year>2012</year>
	<season>5</season>
	<episode>11</episode>
	</meta>
	<link>https://rg.to/file/88730c26483af0c3b6370412915ec88f/Murdoch.Mysteries.S05E11.DVDRip.XviD-OSiTV.avi.html</link>
	<thumbnail>https://image.tmdb.org/t/p/w1280/3op6YCbhKxYWAVymmqaqdLOpDdj.jpg</thumbnail>
	<fanart>https://image.tmdb.org/t/p/w1280/rmIrbTk6Qb08grYwJlGQok9VnGk.jpg</fanart>
</item>
<item>
	<title>[COLOR=white]Murdoch Night in Canada[/COLOR]</title>
	<meta>
	<imdb>tt1091909</imdb>
	<content>episode</content>
	<tvshowtitle>Murdoch Mysteries</tvshowtitle>
	<year>2012</year>
	<season>5</season>
	<episode>12</episode>
	</meta>
	<link>https://rg.to/file/5daac2506d150d0476a95c9f644228a7/Murdoch.Mysteries.S05E12.murdoch.night.in.canada.avi.html</link>
	<thumbnail>https://image.tmdb.org/t/p/w1280/ceVRYstLB62AaGXHWfKXibNZabp.jpg</thumbnail>
	<fanart>https://image.tmdb.org/t/p/w1280/rmIrbTk6Qb08grYwJlGQok9VnGk.jpg</fanart>
</item>
<item>
	<title>[COLOR=white]Twentieth Century Murdoch[/COLOR]</title>
	<meta>
	<imdb>tt1091909</imdb>
	<content>episode</content>
	<tvshowtitle>Murdoch Mysteries</tvshowtitle>
	<year>2012</year>
	<season>5</season>
	<episode>13</episode>
	</meta>
	<link>https://rg.to/file/2c0bcb0d565a8b9cc6247989ddd16bc2/Murdoch.Mysteries.S05E13.DVDRip.XviD-OSiTV.avi.html</link>
	<thumbnail>https://image.tmdb.org/t/p/w1280/japlEJIs1e03CrmTAycg5TDXJuU.jpg</thumbnail>
	<fanart>https://image.tmdb.org/t/p/w1280/rmIrbTk6Qb08grYwJlGQok9VnGk.jpg</fanart>
</item>
