<item>
	<title>[COLOR=white]The Addams Family Goes to School[/COLOR]</title>
	<meta>
	<imdb>tt0057729</imdb>
	<content>episode</content>
	<tvshowtitle>The Addams Family</tvshowtitle>
	<year>1964</year>
	<season>1</season>
	<episode>1</episode>
	</meta>
	<link>https://rapidgator.net/file/30399865e10d4374dcdd2d5b48494d03/1e01-The.Addams.Family.Goes.to.School.mkv.html</link>
	<thumbnail>https://image.tmdb.org/t/p/w1280/14NByLYYUpBCDqBtvN23U9a7mOf.jpg</thumbnail>
	<fanart>https://image.tmdb.org/t/p/w1280/5tL8tlcQuSSszv4nX5fWb4CvN8I.jpg</fanart>
</item>
<item>
	<title>[COLOR=white]Morticia and the Psychiatrist[/COLOR]</title>
	<meta>
	<imdb>tt0057729</imdb>
	<content>episode</content>
	<tvshowtitle>The Addams Family</tvshowtitle>
	<year>1964</year>
	<season>1</season>
	<episode>2</episode>
	</meta>
	<link>https://rapidgator.net/file/4053a8de9064344a7f7b43900db771cd/1e02-Morticia.and.the.Psychiatrist.mkv.html</link>
	<thumbnail>https://image.tmdb.org/t/p/w1280/94IGHpnorAGpBWfx8dXXGgSBVRd.jpg</thumbnail>
	<fanart>https://image.tmdb.org/t/p/w1280/5tL8tlcQuSSszv4nX5fWb4CvN8I.jpg</fanart>
</item>
<item>
	<title>[COLOR=white]Fester's Punctured Romance[/COLOR]</title>
	<meta>
	<imdb>tt0057729</imdb>
	<content>episode</content>
	<tvshowtitle>The Addams Family</tvshowtitle>
	<year>1964</year>
	<season>1</season>
	<episode>3</episode>
	</meta>
	<link>https://rapidgator.net/file/971c7efd857b56163da2dec7914560f7/1e03-Fester.s.Punctured.Romance.mkv.html</link>
	<thumbnail>https://image.tmdb.org/t/p/w1280/4ZS4MOiR8PQoG73pHgp8AH3CuAu.jpg</thumbnail>
	<fanart>https://image.tmdb.org/t/p/w1280/5tL8tlcQuSSszv4nX5fWb4CvN8I.jpg</fanart>
</item>
<item>
	<title>[COLOR=white]Gomez, the Politician[/COLOR]</title>
	<meta>
	<imdb>tt0057729</imdb>
	<content>episode</content>
	<tvshowtitle>The Addams Family</tvshowtitle>
	<year>1964</year>
	<season>1</season>
	<episode>4</episode>
	</meta>
	<link>https://rapidgator.net/file/0c049499228d3fa7d64ea440e573eca4/1e04-Gomez.the.Politician.mkv.html</link>
	<thumbnail>https://image.tmdb.org/t/p/w1280/iBaPtPL6j28AB3nMcBghlwPW9vb.jpg</thumbnail>
	<fanart>https://image.tmdb.org/t/p/w1280/5tL8tlcQuSSszv4nX5fWb4CvN8I.jpg</fanart>
</item>
<item>
	<title>[COLOR=white]The Addams Family Tree[/COLOR]</title>
	<meta>
	<imdb>tt0057729</imdb>
	<content>episode</content>
	<tvshowtitle>The Addams Family</tvshowtitle>
	<year>1964</year>
	<season>1</season>
	<episode>5</episode>
	</meta>
	<link>https://rapidgator.net/file/c510e58c4f608a763ab0e39ea9903362/1e05-The.Addams.Family.Tree.mkv.html</link>
	<thumbnail>https://image.tmdb.org/t/p/w1280/6173j1ViTwVeQFLlD3YL1WevRLT.jpg</thumbnail>
	<fanart>https://image.tmdb.org/t/p/w1280/5tL8tlcQuSSszv4nX5fWb4CvN8I.jpg</fanart>
</item>
<item>
	<title>[COLOR=white]Morticia Joins the Ladies League[/COLOR]</title>
	<meta>
	<imdb>tt0057729</imdb>
	<content>episode</content>
	<tvshowtitle>The Addams Family</tvshowtitle>
	<year>1964</year>
	<season>1</season>
	<episode>6</episode>
	</meta>
	<link>https://rapidgator.net/file/4dfcd2d7c8893e5e7508d73c4b8dd03b/1e06-Morticia.Joins.the.Ladies.League.mkv.html</link>
	<thumbnail>https://image.tmdb.org/t/p/w1280/zUIzRWUIKifgbzeKCKd5vD2CVV.jpg</thumbnail>
	<fanart>https://image.tmdb.org/t/p/w1280/5tL8tlcQuSSszv4nX5fWb4CvN8I.jpg</fanart>
</item>
<item>
	<title>[COLOR=white]Halloween with the Addams Family[/COLOR]</title>
	<meta>
	<imdb>tt0057729</imdb>
	<content>episode</content>
	<tvshowtitle>The Addams Family</tvshowtitle>
	<year>1964</year>
	<season>1</season>
	<episode>7</episode>
	</meta>
	<link>https://rapidgator.net/file/23d6eae3ad89acc8d241a139277137cb/1e07-Halloween.with.the.Addams.Family.mkv.html</link>
	<thumbnail>https://image.tmdb.org/t/p/w1280/fWXdbIT0wOqXynQQrq5GQNQ5nVV.jpg</thumbnail>
	<fanart>https://image.tmdb.org/t/p/w1280/5tL8tlcQuSSszv4nX5fWb4CvN8I.jpg</fanart>
</item>
<item>
	<title>[COLOR=white]Green-Eyed Gomez[/COLOR]</title>
	<meta>
	<imdb>tt0057729</imdb>
	<content>episode</content>
	<tvshowtitle>The Addams Family</tvshowtitle>
	<year>1964</year>
	<season>1</season>
	<episode>8</episode>
	</meta>
	<link>https://rapidgator.net/file/83e2edc0eee4f5750bb27079b7b34b5b/1e08-Green-Eyed.Gomez.mkv.html</link>
	<thumbnail>https://image.tmdb.org/t/p/w1280/l3M64Z3iJ2tenPrl3rjo7EoDF6m.jpg</thumbnail>
	<fanart>https://image.tmdb.org/t/p/w1280/5tL8tlcQuSSszv4nX5fWb4CvN8I.jpg</fanart>
</item>
<item>
	<title>[COLOR=white]The New Neighbors Meet the Addams Family[/COLOR]</title>
	<meta>
	<imdb>tt0057729</imdb>
	<content>episode</content>
	<tvshowtitle>The Addams Family</tvshowtitle>
	<year>1964</year>
	<season>1</season>
	<episode>9</episode>
	</meta>
	<link>https://rapidgator.net/file/2243c6411269ed616cd78ed02b93035d/1e09-The.New.Neighbors.Meet.the.Addams.Family.mkv.html</link>
	<thumbnail>https://image.tmdb.org/t/p/w1280/2nlCWQ7eJNWdLYaJOcy2GfP61zD.jpg</thumbnail>
	<fanart>https://image.tmdb.org/t/p/w1280/5tL8tlcQuSSszv4nX5fWb4CvN8I.jpg</fanart>
</item>
<item>
	<title>[COLOR=white]Wednesday Leaves Home[/COLOR]</title>
	<meta>
	<imdb>tt0057729</imdb>
	<content>episode</content>
	<tvshowtitle>The Addams Family</tvshowtitle>
	<year>1964</year>
	<season>1</season>
	<episode>10</episode>
	</meta>
	<link>https://rapidgator.net/file/80fa32a1f8712073b4516ab39d33746a/1e10-Wednesday.Leaves.Home.mkv.html</link>
	<thumbnail>https://image.tmdb.org/t/p/w1280/jNp7TvGQfyiKDKzg8vm2VqBycgV.jpg</thumbnail>
	<fanart>https://image.tmdb.org/t/p/w1280/5tL8tlcQuSSszv4nX5fWb4CvN8I.jpg</fanart>
</item>
<item>
	<title>[COLOR=white]The Addams Family Meet the V.I.P.'s[/COLOR]</title>
	<meta>
	<imdb>tt0057729</imdb>
	<content>episode</content>
	<tvshowtitle>The Addams Family</tvshowtitle>
	<year>1964</year>
	<season>1</season>
	<episode>11</episode>
	</meta>
	<link>https://rapidgator.net/file/6efcbb41a661cb110a500b576b212305/1e11-The.Addams.Family.Meet.the.V.I.P.s.mkv.html</link>
	<thumbnail>https://image.tmdb.org/t/p/w1280/lustPtyczrCduwUayWjP5GwoJUo.jpg</thumbnail>
	<fanart>https://image.tmdb.org/t/p/w1280/5tL8tlcQuSSszv4nX5fWb4CvN8I.jpg</fanart>
</item>
<item>
	<title>[COLOR=white]Morticia, the Matchmaker[/COLOR]</title>
	<meta>
	<imdb>tt0057729</imdb>
	<content>episode</content>
	<tvshowtitle>The Addams Family</tvshowtitle>
	<year>1964</year>
	<season>1</season>
	<episode>12</episode>
	</meta>
	<link>https://rapidgator.net/file/ce258d53e50a0668fb2ceaf78cd07d69/1e12-Morticia.the.Matchmaker.mkv.html</link>
	<thumbnail>https://image.tmdb.org/t/p/w1280/nnInX7OvSDnfy2oNA8RycXLgiV6.jpg</thumbnail>
	<fanart>https://image.tmdb.org/t/p/w1280/5tL8tlcQuSSszv4nX5fWb4CvN8I.jpg</fanart>
</item>
<item>
	<title>[COLOR=white]Lurch Learns to Dance[/COLOR]</title>
	<meta>
	<imdb>tt0057729</imdb>
	<content>episode</content>
	<tvshowtitle>The Addams Family</tvshowtitle>
	<year>1964</year>
	<season>1</season>
	<episode>13</episode>
	</meta>
	<link>https://rapidgator.net/file/7de6ff49599d5ef18ccca57075dc1935/1e13-Lurch.Learns.to.Dance.mkv.html</link>
	<thumbnail>https://image.tmdb.org/t/p/w1280/wNPMS5jJaeUhuR6P8VMV686XbYU.jpg</thumbnail>
	<fanart>https://image.tmdb.org/t/p/w1280/5tL8tlcQuSSszv4nX5fWb4CvN8I.jpg</fanart>
</item>
<item>
	<title>[COLOR=white]Art and the Addams Family[/COLOR]</title>
	<meta>
	<imdb>tt0057729</imdb>
	<content>episode</content>
	<tvshowtitle>The Addams Family</tvshowtitle>
	<year>1964</year>
	<season>1</season>
	<episode>14</episode>
	</meta>
	<link>https://rapidgator.net/file/16d914329b388903c301fc50f32ca3de/1e14-Art.and.the.Addams.Family.mkv.html</link>
	<thumbnail>https://image.tmdb.org/t/p/w1280/lSGrnoL2DxXnjG3GRYcIwSVhETC.jpg</thumbnail>
	<fanart>https://image.tmdb.org/t/p/w1280/5tL8tlcQuSSszv4nX5fWb4CvN8I.jpg</fanart>
</item>
<item>
	<title>[COLOR=white]The Addams Family Meets a Beatnik[/COLOR]</title>
	<meta>
	<imdb>tt0057729</imdb>
	<content>episode</content>
	<tvshowtitle>The Addams Family</tvshowtitle>
	<year>1965</year>
	<season>1</season>
	<episode>15</episode>
	</meta>
	<link>https://rapidgator.net/file/241a1a6403777455c7996e06e2a47f4e/1e15-The.Addams.Family.Meets.a.Beatnik.mkv.html</link>
	<thumbnail>https://image.tmdb.org/t/p/w1280/lYnfepq336nPicf2UnSbVuwTmfw.jpg</thumbnail>
	<fanart>https://image.tmdb.org/t/p/w1280/5tL8tlcQuSSszv4nX5fWb4CvN8I.jpg</fanart>
</item>
<item>
	<title>[COLOR=white]The Addams Family Meets the Undercover Man[/COLOR]</title>
	<meta>
	<imdb>tt0057729</imdb>
	<content>episode</content>
	<tvshowtitle>The Addams Family</tvshowtitle>
	<year>1965</year>
	<season>1</season>
	<episode>16</episode>
	</meta>
	<link>https://rapidgator.net/file/f50f5af1727b6821ff62165eb89003c7/1e16-The.Addams.Family.Meets.the.Undercover.Man.mkv.html</link>
	<thumbnail>https://image.tmdb.org/t/p/w1280/22XOM6yzhLSXWiRhlYiJkWwD5kU.jpg</thumbnail>
	<fanart>https://image.tmdb.org/t/p/w1280/5tL8tlcQuSSszv4nX5fWb4CvN8I.jpg</fanart>
</item>
<item>
	<title>[COLOR=white]Mother Lurch Visits the Addams Family[/COLOR]</title>
	<meta>
	<imdb>tt0057729</imdb>
	<content>episode</content>
	<tvshowtitle>The Addams Family</tvshowtitle>
	<year>1965</year>
	<season>1</season>
	<episode>17</episode>
	</meta>
	<link>https://rapidgator.net/file/9759b08a753970ce559b538b6469d15b/1e17-Mother.Lurch.Visits.the.Addams.Family.mkv.html</link>
	<thumbnail>https://image.tmdb.org/t/p/w1280/sFtuUBEETYs3xqxCxFdw0jkDBmM.jpg</thumbnail>
	<fanart>https://image.tmdb.org/t/p/w1280/5tL8tlcQuSSszv4nX5fWb4CvN8I.jpg</fanart>
</item>
<item>
	<title>[COLOR=white]Uncle Fester's Illness[/COLOR]</title>
	<meta>
	<imdb>tt0057729</imdb>
	<content>episode</content>
	<tvshowtitle>The Addams Family</tvshowtitle>
	<year>1965</year>
	<season>1</season>
	<episode>18</episode>
	</meta>
	<link>https://rapidgator.net/file/26e1b52cab4ac3a04379fe1ec866c576/1e18-Uncle.Fester.s.Illness.mkv.html</link>
	<thumbnail>https://image.tmdb.org/t/p/w1280/Amarta9bM6hK1FohDBBikrlrT4U.jpg</thumbnail>
	<fanart>https://image.tmdb.org/t/p/w1280/5tL8tlcQuSSszv4nX5fWb4CvN8I.jpg</fanart>
</item>
<item>
	<title>[COLOR=white]The Addams Family Splurges[/COLOR]</title>
	<meta>
	<imdb>tt0057729</imdb>
	<content>episode</content>
	<tvshowtitle>The Addams Family</tvshowtitle>
	<year>1965</year>
	<season>1</season>
	<episode>19</episode>
	</meta>
	<link>https://rg.to/file/2250a3d45e1a193f873b7a6213fcc367/The.Addams.Family.1964.S01E19.mp4.html</link>
	<thumbnail>https://image.tmdb.org/t/p/w1280/bTKpIkF3RuFi8GVwWE6YVOzcpjg.jpg</thumbnail>
	<fanart>https://image.tmdb.org/t/p/w1280/5tL8tlcQuSSszv4nX5fWb4CvN8I.jpg</fanart>
</item>
<item>
	<title>[COLOR=white]Cousin Itt Visits the Addams Family[/COLOR]</title>
	<meta>
	<imdb>tt0057729</imdb>
	<content>episode</content>
	<tvshowtitle>The Addams Family</tvshowtitle>
	<year>1965</year>
	<season>1</season>
	<episode>20</episode>
	</meta>
	<link>https://rapidgator.net/file/6b34266db3e2fe686ed5480d307ff605/1e20-Cousin.Itt.Visits.the.Addams.Family.mkv.html</link>
	<thumbnail>https://image.tmdb.org/t/p/w1280/yZnG1SEYbk43qCqAai6b0PSzJhe.jpg</thumbnail>
	<fanart>https://image.tmdb.org/t/p/w1280/5tL8tlcQuSSszv4nX5fWb4CvN8I.jpg</fanart>
</item>
<item>
	<title>[COLOR=white]The Addams Family in Court[/COLOR]</title>
	<meta>
	<imdb>tt0057729</imdb>
	<content>episode</content>
	<tvshowtitle>The Addams Family</tvshowtitle>
	<year>1965</year>
	<season>1</season>
	<episode>21</episode>
	</meta>
	<link>https://rapidgator.net/file/5d4f7a866080b6dad2ffc737d4515213/1e21-The.Addams.Family.in.Court.mkv.html</link>
	<thumbnail>https://image.tmdb.org/t/p/w1280/4NfUbKWOv2Xyhzz7NFC5AVWgxYD.jpg</thumbnail>
	<fanart>https://image.tmdb.org/t/p/w1280/5tL8tlcQuSSszv4nX5fWb4CvN8I.jpg</fanart>
</item>
<item>
	<title>[COLOR=white]Amnesia in the Addams Family[/COLOR]</title>
	<meta>
	<imdb>tt0057729</imdb>
	<content>episode</content>
	<tvshowtitle>The Addams Family</tvshowtitle>
	<year>1965</year>
	<season>1</season>
	<episode>22</episode>
	</meta>
	<link>https://rapidgator.net/file/824f87160ed74304e3ac31d2699a9c62/1e22-Amnesia.in.the.Addams.Family.mkv.html</link>
	<thumbnail>https://image.tmdb.org/t/p/w1280/5kHJPGZf8bXaws8j06VvkS84OIT.jpg</thumbnail>
	<fanart>https://image.tmdb.org/t/p/w1280/5tL8tlcQuSSszv4nX5fWb4CvN8I.jpg</fanart>
</item>
<item>
	<title>[COLOR=white]Thing is Missing[/COLOR]</title>
	<meta>
	<imdb>tt0057729</imdb>
	<content>episode</content>
	<tvshowtitle>The Addams Family</tvshowtitle>
	<year>1965</year>
	<season>1</season>
	<episode>23</episode>
	</meta>
	<link>https://rapidgator.net/file/3ccf6f654f44dfe611898f3755e8ed73/1e23-Thing.is.Missing.mkv.html</link>
	<thumbnail>https://image.tmdb.org/t/p/w1280/dLOrSxYnNpXqu0k2cfkzrmHVgVg.jpg</thumbnail>
	<fanart>https://image.tmdb.org/t/p/w1280/5tL8tlcQuSSszv4nX5fWb4CvN8I.jpg</fanart>
</item>
<item>
	<title>[COLOR=white]Crisis in the Addams Family[/COLOR]</title>
	<meta>
	<imdb>tt0057729</imdb>
	<content>episode</content>
	<tvshowtitle>The Addams Family</tvshowtitle>
	<year>1965</year>
	<season>1</season>
	<episode>24</episode>
	</meta>
	<link>https://rapidgator.net/file/3803b5056e5cd1de3eb00a3915c3717b/1e24-Crisis.in.the.Addams.Family.mkv.html</link>
	<thumbnail>https://image.tmdb.org/t/p/w1280/bfKwACUAWXpivfMEC9D65IvkuBm.jpg</thumbnail>
	<fanart>https://image.tmdb.org/t/p/w1280/5tL8tlcQuSSszv4nX5fWb4CvN8I.jpg</fanart>
</item>
<item>
	<title>[COLOR=white]Lurch and His Harpsichord[/COLOR]</title>
	<meta>
	<imdb>tt0057729</imdb>
	<content>episode</content>
	<tvshowtitle>The Addams Family</tvshowtitle>
	<year>1965</year>
	<season>1</season>
	<episode>25</episode>
	</meta>
	<link>https://rapidgator.net/file/21e96e1a868a7c632e7b936d11214186/1e25-Lurch.and.His.Harpsichord.mkv.html</link>
	<thumbnail>https://image.tmdb.org/t/p/w1280/o9iYdaJabAXx8COhog3nkJYfki8.jpg</thumbnail>
	<fanart>https://image.tmdb.org/t/p/w1280/5tL8tlcQuSSszv4nX5fWb4CvN8I.jpg</fanart>
</item>
<item>
	<title>[COLOR=white]Morticia, the Breadwinner[/COLOR]</title>
	<meta>
	<imdb>tt0057729</imdb>
	<content>episode</content>
	<tvshowtitle>The Addams Family</tvshowtitle>
	<year>1965</year>
	<season>1</season>
	<episode>26</episode>
	</meta>
	<link>https://rapidgator.net/file/dd0ecc0e8d7a93e19ccfe38d602953ab/1e26-Morticia.the.Breadwinner.mkv.html</link>
	<thumbnail>https://image.tmdb.org/t/p/w1280/bCKxzvfQbH8aKt50ajb1rPYOKGc.jpg</thumbnail>
	<fanart>https://image.tmdb.org/t/p/w1280/5tL8tlcQuSSszv4nX5fWb4CvN8I.jpg</fanart>
</item>
<item>
	<title>[COLOR=white]The Addams Family and the Spacemen[/COLOR]</title>
	<meta>
	<imdb>tt0057729</imdb>
	<content>episode</content>
	<tvshowtitle>The Addams Family</tvshowtitle>
	<year>1965</year>
	<season>1</season>
	<episode>27</episode>
	</meta>
	<link>https://rapidgator.net/file/cd5f1514cc2d81a918684dd99e558f1d/1e27-The.Addams.Family.and.the.Spacemen.mkv.html</link>
	<thumbnail>https://image.tmdb.org/t/p/w1280/Ab2LbSEeLaQvuCTPf9RJLfLrO1K.jpg</thumbnail>
	<fanart>https://image.tmdb.org/t/p/w1280/5tL8tlcQuSSszv4nX5fWb4CvN8I.jpg</fanart>
</item>
<item>
	<title>[COLOR=white]My Son, the Chimp[/COLOR]</title>
	<meta>
	<imdb>tt0057729</imdb>
	<content>episode</content>
	<tvshowtitle>The Addams Family</tvshowtitle>
	<year>1965</year>
	<season>1</season>
	<episode>28</episode>
	</meta>
	<link>https://rapidgator.net/file/a582fecd9ab000f2d29f6f7fe0f32e81/1e28-My.Son.the.Chimp.mkv.html</link>
	<thumbnail>https://image.tmdb.org/t/p/w1280/aMuw1dOb8yUdUCAdb1VyS9bih73.jpg</thumbnail>
	<fanart>https://image.tmdb.org/t/p/w1280/5tL8tlcQuSSszv4nX5fWb4CvN8I.jpg</fanart>
</item>
<item>
	<title>[COLOR=white]Morticia's Favorite Charity[/COLOR]</title>
	<meta>
	<imdb>tt0057729</imdb>
	<content>episode</content>
	<tvshowtitle>The Addams Family</tvshowtitle>
	<year>1965</year>
	<season>1</season>
	<episode>29</episode>
	</meta>
	<link>https://rapidgator.net/file/6ba9bd3c8f5635e37da173e539e470e2/1e29-Morticia.s.Favorite.Charity.mkv.html</link>
	<thumbnail>https://image.tmdb.org/t/p/w1280/sRCeyMbuU0Ywh07QMulLU5QKJs9.jpg</thumbnail>
	<fanart>https://image.tmdb.org/t/p/w1280/5tL8tlcQuSSszv4nX5fWb4CvN8I.jpg</fanart>
</item>
<item>
	<title>[COLOR=white]Progress and the Addams Family[/COLOR]</title>
	<meta>
	<imdb>tt0057729</imdb>
	<content>episode</content>
	<tvshowtitle>The Addams Family</tvshowtitle>
	<year>1965</year>
	<season>1</season>
	<episode>30</episode>
	</meta>
	<link>https://rapidgator.net/file/b14fb973563c1617bf31c8f041888535/1e30-Progress.and.the.Addams.Family.mkv.html</link>
	<thumbnail>https://image.tmdb.org/t/p/w1280/g2HGNNVmoXvH78v366rGNRBV4bE.jpg</thumbnail>
	<fanart>https://image.tmdb.org/t/p/w1280/5tL8tlcQuSSszv4nX5fWb4CvN8I.jpg</fanart>
</item>
<item>
	<title>[COLOR=white]Uncle Fester's Toupee[/COLOR]</title>
	<meta>
	<imdb>tt0057729</imdb>
	<content>episode</content>
	<tvshowtitle>The Addams Family</tvshowtitle>
	<year>1965</year>
	<season>1</season>
	<episode>31</episode>
	</meta>
	<link>https://rapidgator.net/file/b66f9c3c5690f38aab8cd2f625d7d0cf/1e31-Uncle.Fester.s.Toupee.mkv.html</link>
	<thumbnail>https://image.tmdb.org/t/p/w1280/17DURlcDShrOSMttIdn5hncnse4.jpg</thumbnail>
	<fanart>https://image.tmdb.org/t/p/w1280/5tL8tlcQuSSszv4nX5fWb4CvN8I.jpg</fanart>
</item>
<item>
	<title>[COLOR=white]Cousin Itt and the Vocational Counselor[/COLOR]</title>
	<meta>
	<imdb>tt0057729</imdb>
	<content>episode</content>
	<tvshowtitle>The Addams Family</tvshowtitle>
	<year>1965</year>
	<season>1</season>
	<episode>32</episode>
	</meta>
	<link>https://rapidgator.net/file/0bedad51cc7dec38fcc00e3a4b305b76/1e32-Cousin.Itt.and.the.Vocational.Counselor.mkv.html</link>
	<thumbnail>https://image.tmdb.org/t/p/w1280/u3I53RVZ1TX7WopTqH9BRELFb5c.jpg</thumbnail>
	<fanart>https://image.tmdb.org/t/p/w1280/5tL8tlcQuSSszv4nX5fWb4CvN8I.jpg</fanart>
</item>
<item>
	<title>[COLOR=white]Lurch, the Teenage Idol[/COLOR]</title>
	<meta>
	<imdb>tt0057729</imdb>
	<content>episode</content>
	<tvshowtitle>The Addams Family</tvshowtitle>
	<year>1965</year>
	<season>1</season>
	<episode>33</episode>
	</meta>
	<link>https://rapidgator.net/file/4feef3e39a7431a5d00a8c8599226b1a/1e33-Lurch.the.tenage.Idol.mkv.html</link>
	<thumbnail>https://image.tmdb.org/t/p/w1280/wWcgi35ptaPLFs3bmYb40Wnhpq4.jpg</thumbnail>
	<fanart>https://image.tmdb.org/t/p/w1280/5tL8tlcQuSSszv4nX5fWb4CvN8I.jpg</fanart>
</item>
<item>
	<title>[COLOR=white]The Winning of Morticia Addams[/COLOR]</title>
	<meta>
	<imdb>tt0057729</imdb>
	<content>episode</content>
	<tvshowtitle>The Addams Family</tvshowtitle>
	<year>1965</year>
	<season>1</season>
	<episode>34</episode>
	</meta>
	<link>https://rapidgator.net/file/f5d64859b929aa15c4a2699db79acbcb/1e34-The.Winning.of.Morticia.Addams.mkv.html</link>
	<thumbnail>https://image.tmdb.org/t/p/w1280/5K0y6QdzEE3G27Ywpz7jrd4KUKF.jpg</thumbnail>
	<fanart>https://image.tmdb.org/t/p/w1280/5tL8tlcQuSSszv4nX5fWb4CvN8I.jpg</fanart>
</item>
