<item>
	<title>[COLOR=white]Murder from Above[/COLOR]</title>
	<meta>
	<imdb>tt1888075</imdb>
	<content>episode</content>
	<tvshowtitle>Death in Paradise</tvshowtitle>
	<year>2018</year>
	<season>7</season>
	<episode>1</episode>
	</meta>
	<link>https://luluvid.com/uaz9nsk1hfw9</link>
	<thumbnail>https://image.tmdb.org/t/p/w1280/bD59TjzUOUolprPjGEFr7MXONXw.jpg</thumbnail>
	<fanart>https://image.tmdb.org/t/p/w1280/h7EnqIFoEaDO36gqS7VqAyPhLuG.jpg</fanart>
</item>
<item>
	<title>[COLOR=white]The Stakes Are High[/COLOR]</title>
	<meta>
	<imdb>tt1888075</imdb>
	<content>episode</content>
	<tvshowtitle>Death in Paradise</tvshowtitle>
	<year>2018</year>
	<season>7</season>
	<episode>2</episode>
	</meta>
	<link>https://luluvid.com/sd6nybgt9sxz</link>
	<thumbnail>https://image.tmdb.org/t/p/w1280/bKI5XBNCllt4YnuMOPM3Dfh2PD6.jpg</thumbnail>
	<fanart>https://image.tmdb.org/t/p/w1280/h7EnqIFoEaDO36gqS7VqAyPhLuG.jpg</fanart>
</item>
<item>
	<title>[COLOR=white]Written in Murder[/COLOR]</title>
	<meta>
	<imdb>tt1888075</imdb>
	<content>episode</content>
	<tvshowtitle>Death in Paradise</tvshowtitle>
	<year>2018</year>
	<season>7</season>
	<episode>3</episode>
	</meta>
	<link>https://luluvid.com/ju1uys1p2ql3</link>
	<thumbnail>https://image.tmdb.org/t/p/w1280/fCXkQ7cTTaMyRFgoA5yqRffJk4n.jpg</thumbnail>
	<fanart>https://image.tmdb.org/t/p/w1280/h7EnqIFoEaDO36gqS7VqAyPhLuG.jpg</fanart>
</item>
<item>
	<title>[COLOR=white]The Healer[/COLOR]</title>
	<meta>
	<imdb>tt1888075</imdb>
	<content>episode</content>
	<tvshowtitle>Death in Paradise</tvshowtitle>
	<year>2018</year>
	<season>7</season>
	<episode>4</episode>
	</meta>
	<link>https://luluvid.com/3sak292bsnl7</link>
	<thumbnail>https://image.tmdb.org/t/p/w1280/2Fpv5scQ1vPaQzwmezAi8p7X98S.jpg</thumbnail>
	<fanart>https://image.tmdb.org/t/p/w1280/h7EnqIFoEaDO36gqS7VqAyPhLuG.jpg</fanart>
</item>
<item>
	<title>[COLOR=white]Murder on the Day of the Dead[/COLOR]</title>
	<meta>
	<imdb>tt1888075</imdb>
	<content>episode</content>
	<tvshowtitle>Death in Paradise</tvshowtitle>
	<year>2018</year>
	<season>7</season>
	<episode>5</episode>
	</meta>
	<link>https://luluvid.com/36ejjkc72750</link>
	<thumbnail>https://image.tmdb.org/t/p/w1280/oqwkxKck1NgChzJkLJ7pFoW57AE.jpg</thumbnail>
	<fanart>https://image.tmdb.org/t/p/w1280/h7EnqIFoEaDO36gqS7VqAyPhLuG.jpg</fanart>
</item>
<item>
	<title>[COLOR=white]Meditated in Murder[/COLOR]</title>
	<meta>
	<imdb>tt1888075</imdb>
	<content>episode</content>
	<tvshowtitle>Death in Paradise</tvshowtitle>
	<year>2018</year>
	<season>7</season>
	<episode>6</episode>
	</meta>
	<link>https://luluvid.com/9j6r3bsbpa0a</link>
	<thumbnail>https://image.tmdb.org/t/p/w1280/iy7XStjqp5orciasgRkOCOzNNAR.jpg</thumbnail>
	<fanart>https://image.tmdb.org/t/p/w1280/h7EnqIFoEaDO36gqS7VqAyPhLuG.jpg</fanart>
</item>
<item>
	<title>[COLOR=white]Dark Memories[/COLOR]</title>
	<meta>
	<imdb>tt1888075</imdb>
	<content>episode</content>
	<tvshowtitle>Death in Paradise</tvshowtitle>
	<year>2018</year>
	<season>7</season>
	<episode>7</episode>
	</meta>
	<link>https://luluvid.com/727sxcer1y0f</link>
	<thumbnail>https://image.tmdb.org/t/p/w1280/aVq4j6SidgcHFueZkDf9iKEvGpe.jpg</thumbnail>
	<fanart>https://image.tmdb.org/t/p/w1280/h7EnqIFoEaDO36gqS7VqAyPhLuG.jpg</fanart>
</item>
<item>
	<title>[COLOR=white]Melodies of Murder[/COLOR]</title>
	<meta>
	<imdb>tt1888075</imdb>
	<content>episode</content>
	<tvshowtitle>Death in Paradise</tvshowtitle>
	<year>2018</year>
	<season>7</season>
	<episode>8</episode>
	</meta>
	<link>https://luluvid.com/j2f2np96fltn</link>
	<thumbnail>https://image.tmdb.org/t/p/w1280/z8AeJ7pdiA1ILXagZFPvCBfKYSf.jpg</thumbnail>
	<fanart>https://image.tmdb.org/t/p/w1280/h7EnqIFoEaDO36gqS7VqAyPhLuG.jpg</fanart>
</item>

