<item>
	<title>[COLOR=white]Chance Encounters[/COLOR]</title>
	<meta>
	<imdb>tt9698442</imdb>
	<content>episode</content>
	<tvshowtitle>Behind Her Eyes</tvshowtitle>
	<year>2021</year>
	<season>1</season>
	<episode>1</episode>
	</meta>
	<link>https://rapidgator.net/file/68ace8f4000ad17dee85cfcd93d32d3b/Behind.Her.Eyes.S01E01.Chance.Encounters.1080p.NF.WEB-DL.DDP5.1.Atmos.x264-iKA.mkv.html</link>
	<thumbnail>https://image.tmdb.org/t/p/w1280/5KnHlYv5LkjdMIbFF4FNIoy1ZKU.jpg</thumbnail>
	<fanart>https://image.tmdb.org/t/p/w1280/w99Pk4pJSieveKIIc7KGXtsFT3U.jpg</fanart>
</item>
<item>
	<title>[COLOR=white]Lucid Dreaming[/COLOR]</title>
	<meta>
	<imdb>tt9698442</imdb>
	<content>episode</content>
	<tvshowtitle>Behind Her Eyes</tvshowtitle>
	<year>2021</year>
	<season>1</season>
	<episode>2</episode>
	</meta>
	<link>https://rapidgator.net/file/f3116237698f9e60bc4b9d88f040d4a9/Behind.Her.Eyes.S01E02.Lucid.Dreaming.1080p.NF.WEB-DL.DDP5.1.Atmos.x264-iKA.mkv.html</link>
	<thumbnail>https://image.tmdb.org/t/p/w1280/3mbDMHuICDWMdiChH8mkPIhiVz8.jpg</thumbnail>
	<fanart>https://image.tmdb.org/t/p/w1280/w99Pk4pJSieveKIIc7KGXtsFT3U.jpg</fanart>
</item>
<item>
	<title>[COLOR=white]The First Door[/COLOR]</title>
	<meta>
	<imdb>tt9698442</imdb>
	<content>episode</content>
	<tvshowtitle>Behind Her Eyes</tvshowtitle>
	<year>2021</year>
	<season>1</season>
	<episode>3</episode>
	</meta>
	<link>https://rapidgator.net/file/f50c45dbce5702d492e1f03166e936c2/Behind.Her.Eyes.S01E03.the.First.Door.1080p.NF.WEB-DL.DDP5.1.Atmos.x264-iKA.mkv.html</link>
	<thumbnail>https://image.tmdb.org/t/p/w1280/2oFuknmzJgb8IHQ697am6blxthK.jpg</thumbnail>
	<fanart>https://image.tmdb.org/t/p/w1280/w99Pk4pJSieveKIIc7KGXtsFT3U.jpg</fanart>
</item>
<item>
	<title>[COLOR=white]Rob[/COLOR]</title>
	<meta>
	<imdb>tt9698442</imdb>
	<content>episode</content>
	<tvshowtitle>Behind Her Eyes</tvshowtitle>
	<year>2021</year>
	<season>1</season>
	<episode>4</episode>
	</meta>
	<link>https://rapidgator.net/file/373fa5aa82b884491851a6f6e71330d3/Behind.Her.Eyes.S01E04.Rob.1080p.NF.WEB-DL.DDP5.1.Atmos.x264-iKA.mkv.html</link>
	<thumbnail>https://image.tmdb.org/t/p/w1280/v2YJWofcF6phrbCy8m95XI31hG.jpg</thumbnail>
	<fanart>https://image.tmdb.org/t/p/w1280/w99Pk4pJSieveKIIc7KGXtsFT3U.jpg</fanart>
</item>
<item>
	<title>[COLOR=white]The Second Door[/COLOR]</title>
	<meta>
	<imdb>tt9698442</imdb>
	<content>episode</content>
	<tvshowtitle>Behind Her Eyes</tvshowtitle>
	<year>2021</year>
	<season>1</season>
	<episode>5</episode>
	</meta>
	<link>https://rapidgator.net/file/e8183088e854af8162c2762a3e789da3/Behind.Her.Eyes.S01E05.the.Second.Door.1080p.NF.WEB-DL.DDP5.1.Atmos.x264-iKA.mkv.html</link>
	<thumbnail>https://image.tmdb.org/t/p/w1280/l93l1ouiijoZRofpNdEnahNcjK0.jpg</thumbnail>
	<fanart>https://image.tmdb.org/t/p/w1280/w99Pk4pJSieveKIIc7KGXtsFT3U.jpg</fanart>
</item>
<item>
	<title>[COLOR=white]Behind Her Eyes[/COLOR]</title>
	<meta>
	<imdb>tt9698442</imdb>
	<content>episode</content>
	<tvshowtitle>Behind Her Eyes</tvshowtitle>
	<year>2021</year>
	<season>1</season>
	<episode>6</episode>
	</meta>
	<link>https://rapidgator.net/file/ac9a02b4c3eca2cc4428c3f879bd14ec/Behind.Her.Eyes.S01E06.Behind.Her.Eyes.1080p.NF.WEB-DL.DDP5.1.Atmos.x264-iKA.mkv.html</link>
	<thumbnail>https://image.tmdb.org/t/p/w1280/yTxd7BdELtHg5RDEWkS0nNvwRrl.jpg</thumbnail>
	<fanart>https://image.tmdb.org/t/p/w1280/w99Pk4pJSieveKIIc7KGXtsFT3U.jpg</fanart>
</item>
