
<dir>
	<title>[COLOR=white]Season 1[/COLOR]</title>
	<meta>
	<imdb>tt0306414</imdb>
	<content>season</content>
	<season>1</season>
	<year>2002</year>
	</meta>
	<link>http://www.ezzer-mac.com/Addon/text/tvseries/thewire/thewire1.xml</link>
	<thumbnail>https://image.tmdb.org/t/p/w1280/blgnd2APWtxsxGyctmZyaMPO4Ym.jpg</thumbnail>
	<fanart>https://image.tmdb.org/t/p/w1280/oggnxmvofLtGQvXsO9bAFyCj3p6.jpg</fanart>
</dir>
<dir>
	<title>[COLOR=white]Season 2[/COLOR]</title>
	<meta>
	<imdb>tt0306414</imdb>
	<content>season</content>
	<season>2</season>
	<year>2003</year>
	</meta>
	<link>http://www.ezzer-mac.com/Addon/text/tvseries/thewire/thewire2.xml</link>
	<thumbnail>https://image.tmdb.org/t/p/w1280/scOZiOzUePpz7JnWRpjI8HcY1RU.jpg</thumbnail>
	<fanart>https://image.tmdb.org/t/p/w1280/oggnxmvofLtGQvXsO9bAFyCj3p6.jpg</fanart>
</dir>
<dir>
	<title>[COLOR=white]Season 3[/COLOR]</title>
	<meta>
	<imdb>tt0306414</imdb>
	<content>season</content>
	<season>3</season>
	<year>2004</year>
	</meta>
	<link>http://www.ezzer-mac.com/Addon/text/tvseries/thewire/thewire3.xml</link>
	<thumbnail>https://image.tmdb.org/t/p/w1280/mWo4dHE0XXsKgZOQQCtkHl3IHrf.jpg</thumbnail>
	<fanart>https://image.tmdb.org/t/p/w1280/oggnxmvofLtGQvXsO9bAFyCj3p6.jpg</fanart>
</dir>
<dir>
	<title>[COLOR=white]Season 4[/COLOR]</title>
	<meta>
	<imdb>tt0306414</imdb>
	<content>season</content>
	<season>4</season>
	<year>2006</year>
	</meta>
	<link>http://www.ezzer-mac.com/Addon/text/tvseries/thewire/thewire4.xml</link>
	<thumbnail>https://image.tmdb.org/t/p/w1280/jxSJdEX6jmODu3eglC8j4Kv2Gll.jpg</thumbnail>
	<fanart>https://image.tmdb.org/t/p/w1280/oggnxmvofLtGQvXsO9bAFyCj3p6.jpg</fanart>
</dir>
<dir>
	<title>[COLOR=white]Season 5[/COLOR]</title>
	<meta>
	<imdb>tt0306414</imdb>
	<content>season</content>
	<season>5</season>
	<year>2008</year>
	</meta>
	<link>http://www.ezzer-mac.com/Addon/text/tvseries/thewire/thewire5.xml</link>
	<thumbnail>https://image.tmdb.org/t/p/w1280/eAU1JwadhNBar0xaxxVW3frlkM5.jpg</thumbnail>
	<fanart>https://image.tmdb.org/t/p/w1280/oggnxmvofLtGQvXsO9bAFyCj3p6.jpg</fanart>
</dir>
