<item>
	<title>[COLOR=white]Widows II: Episode 1[/COLOR]</title>
	<meta>
	<imdb>tt0085111</imdb>
	<content>episode</content>
	<tvshowtitle>Widows</tvshowtitle>
	<year>1985</year>
	<season>2</season>
	<episode>1</episode>
	</meta>
	<link>https://rg.to/file/f951207310cecadc41ac486cc09906c6/Widows.S02E01.avi.html</link>
	<thumbnail>https://image.tmdb.org/t/p/w1280</thumbnail>
	<fanart>https://image.tmdb.org/t/p/w1280None</fanart>
</item>
<item>
	<title>[COLOR=white]Widows II: Episode 2[/COLOR]</title>
	<meta>
	<imdb>tt0085111</imdb>
	<content>episode</content>
	<tvshowtitle>Widows</tvshowtitle>
	<year>1985</year>
	<season>2</season>
	<episode>2</episode>
	</meta>
	<link>https://rg.to/file/c8ec6674425f2d9e58d90bf44d750908/Widows.S02E02.avi.html</link>
	<thumbnail>https://image.tmdb.org/t/p/w1280</thumbnail>
	<fanart>https://image.tmdb.org/t/p/w1280None</fanart>
</item>
<item>
	<title>[COLOR=white]Widows II: Episode 3[/COLOR]</title>
	<meta>
	<imdb>tt0085111</imdb>
	<content>episode</content>
	<tvshowtitle>Widows</tvshowtitle>
	<year>1985</year>
	<season>2</season>
	<episode>3</episode>
	</meta>
	<link>https://rg.to/file/4a4274796fa2deab3151805df1382b3c/Widows.S02E03.avi.html</link>
	<thumbnail>https://image.tmdb.org/t/p/w1280</thumbnail>
	<fanart>https://image.tmdb.org/t/p/w1280None</fanart>
</item>
<item>
	<title>[COLOR=white]Widows II: Episode 4[/COLOR]</title>
	<meta>
	<imdb>tt0085111</imdb>
	<content>episode</content>
	<tvshowtitle>Widows</tvshowtitle>
	<year>1985</year>
	<season>2</season>
	<episode>4</episode>
	</meta>
	<link>https://rg.to/file/0524370294c378ac71b58b77ecd02e82/Widows.S02E04.avi.html</link>
	<thumbnail>https://image.tmdb.org/t/p/w1280</thumbnail>
	<fanart>https://image.tmdb.org/t/p/w1280None</fanart>
</item>
<item>
	<title>[COLOR=white]Widows II: Episode 5[/COLOR]</title>
	<meta>
	<imdb>tt0085111</imdb>
	<content>episode</content>
	<tvshowtitle>Widows</tvshowtitle>
	<year>1985</year>
	<season>2</season>
	<episode>5</episode>
	</meta>
	<link>https://rg.to/file/409b623c59221826c537a1c56e14b93d/Widows.S02E05.mkv.html</link>
	<thumbnail>https://image.tmdb.org/t/p/w1280</thumbnail>
	<fanart>https://image.tmdb.org/t/p/w1280None</fanart>
</item>
<item>
	<title>[COLOR=white]Widows II: Episode 6[/COLOR]</title>
	<meta>
	<imdb>tt0085111</imdb>
	<content>episode</content>
	<tvshowtitle>Widows</tvshowtitle>
	<year>1985</year>
	<season>2</season>
	<episode>6</episode>
	</meta>
	<link>https://rg.to/file/c31bd1c1a5c280d48e5832ebbfbb3d05/Widows.S02E06.mkv.html</link>
	<thumbnail>https://image.tmdb.org/t/p/w1280</thumbnail>
	<fanart>https://image.tmdb.org/t/p/w1280None</fanart>
</item>
